pyth/__init__.py
pyth/document.py
pyth/errors.py
pyth/format.py
pyth/encodings/__init__.py
pyth/encodings/symbol.py
pyth/plugins/__init__.py
pyth/plugins/latex/__init__.py
pyth/plugins/latex/writer.py
pyth/plugins/pdf/__init__.py
pyth/plugins/pdf/writer.py
pyth/plugins/plaintext/__init__.py
pyth/plugins/plaintext/writer.py
pyth/plugins/python/__init__.py
pyth/plugins/python/reader.py
pyth/plugins/rst/__init__.py
pyth/plugins/rst/writer.py
pyth/plugins/rtf15/__init__.py
pyth/plugins/rtf15/reader.py
pyth/plugins/rtf15/writer.py
pyth/plugins/xhtml/__init__.py
pyth/plugins/xhtml/css.py
pyth/plugins/xhtml/reader.py
pyth/plugins/xhtml/writer.py
pyth3_reloaded-0.8.dist-info/LICENSE
pyth3_reloaded-0.8.dist-info/METADATA
pyth3_reloaded-0.8.dist-info/WHEEL
pyth3_reloaded-0.8.dist-info/top_level.txt
pyth3_reloaded-0.8.dist-info/RECORD
